airflowctl/__init__.py
airflowctl/__main__.py
airflowctl/cli.py
airflowctl/dags/example_dag_basic.py
airflowctl/modes/__init__.py
airflowctl/modes/virtualenv.py
airflowctl/scripts/add_connections.py
airflowctl/scripts/add_variables.py
airflowctl/utils/__init__.py
airflowctl/utils/connections.py
airflowctl/utils/install_airflow.py
airflowctl/utils/paths.py
airflowctl/utils/project.py
airflowctl/utils/variables.py
airflowctl-0.2.9.dist-info/LICENSE
airflowctl-0.2.9.dist-info/METADATA
airflowctl-0.2.9.dist-info/WHEEL
airflowctl-0.2.9.dist-info/entry_points.txt
airflowctl-0.2.9.dist-info/RECORD
